binance_ohlcv-0.0.3.dist-info/METADATA
binance_ohlcv-0.0.3.dist-info/WHEEL
binance_ohlcv-0.0.3.dist-info/licenses/LICENSE
binance_ohlcv/__init__.py
binance_ohlcv/_async.py
binance_ohlcv/_ohlcv.py
binance_ohlcv-0.0.3.dist-info/RECORD
