Metadata-Version: 2.1
Name: binance-ohlcv
Version: 0.0.3
Summary: Get OHLCV/klines/candlesticks data from binance.
Author-Email: Meng Xiangzhuo <aumo@foxmail.com>
License: MIT
Requires-Python: <3.13,>=3.9
Requires-Dist: pandas>=2.1.2
Requires-Dist: httpx>=0.25.0
